pyqsync/__init__.py
pyqsync/__main__.py
pyqsync/base.py
pyqsync/client_adb.py
pyqsync/client_lft.py
pyqsync/client_sftp.py
pyqsync/dubs.py
pyqsync/syncer.py
pyqsync-0.0.6.dist-info/licenses/LICENCE.txt
pyqsync-0.0.6.dist-info/METADATA
pyqsync-0.0.6.dist-info/WHEEL
pyqsync-0.0.6.dist-info/top_level.txt
pyqsync-0.0.6.dist-info/RECORD
