Metadata-Version: 2.4
Name: pyqsync
Version: 0.0.6
Summary: Python module to sync files across different systems(local, sftp, adb)
Author-email: Roman Smolnyk <poma23324@gmail.com>
Project-URL: Homepage, https://github.com/roman-smolnyk/python-pyqsync.git
Keywords: files,dirs,sync
Classifier: Programming Language :: Python :: 3
Classifier: License :: OSI Approved :: MIT License
Classifier: Operating System :: OS Independent
License-File: LICENCE.txt
Requires-Dist: paramiko
Requires-Dist: pure-python-adb
Requires-Dist: ytils
Dynamic: license-file
